dicebear_cli/__init__.py
dicebear_cli/__main__.py
dicebear_cli-1.1.2.dist-info/LICENSE
dicebear_cli-1.1.2.dist-info/METADATA
dicebear_cli-1.1.2.dist-info/WHEEL
dicebear_cli-1.1.2.dist-info/entry_points.txt
dicebear_cli-1.1.2.dist-info/top_level.txt
dicebear_cli-1.1.2.dist-info/RECORD
