Metadata-Version: 2.1
Name: dicebear-cli
Version: 1.1.2
Summary: A Python CLI for DiceBear's avatar generating API.
Home-page: https://github.com/jvherck/dicebear-cli
Author: jvherck
Author-email: jan@vhjan.me
Maintainer: jvherck
Maintainer-email: jan@vhjan.me
License: MIT License
Project-URL: Documentation, https://github.com/jvherck/dicebear-cli/blob/main/README.md
Project-URL: Source, https://github.com/jvherck/dicebear-cli
Project-URL: Tracker, https://github.com/jvherck/dicebear-cli/issues
Keywords: python,dicebear,avatar,avatars,generating,generation,generator,API,wrapper,image,images,picture,pictures,png,jpg,svg,json,cli,pillow,pil,requests,adventurer,adventurer-neutral,avataaars,avataaars-neutral,big-ears,big-ears-neutral,big-smile,bottts,bottts-neutral,croodles,croodles-neutral,fun-emoji,icons,identicon,initials,lorelei,lorelei-neutral,micah,miniavs,notionists,notionists-neutral,open-peeps,personas,pixel-art,pixel-art-neutral,shapes,thumbs
Classifier: Development Status :: 5 - Production/Stable
Classifier: Intended Audience :: Developers
Classifier: Intended Audience :: Other Audience
Classifier: Natural Language :: English
Classifier: Programming Language :: Python :: 3
Classifier: Programming Language :: Python :: 3 :: Only
Classifier: Programming Language :: Python :: 3.8
Classifier: Programming Language :: Python :: 3.9
Classifier: Programming Language :: Python :: 3.10
Classifier: Programming Language :: Python :: 3.11
Classifier: Programming Language :: Python :: 3.12
Classifier: Operating System :: Unix
Classifier: Operating System :: MacOS
Classifier: Operating System :: Microsoft :: Windows
Classifier: License :: OSI Approved :: MIT License
Classifier: Topic :: Artistic Software
Classifier: Topic :: Games/Entertainment
Classifier: Topic :: Multimedia :: Graphics
Classifier: Topic :: Other/Nonlisted Topic
Classifier: Topic :: Software Development :: Libraries :: Python Modules
Requires-Python: >=3.7
License-File: LICENSE
Requires-Dist: dicebear
Requires-Dist: click
